cotengrust-0.2.0.dist-info/METADATA
cotengrust-0.2.0.dist-info/WHEEL
cotengrust-0.2.0.dist-info/licenses/LICENSE
cotengrust/__init__.py
cotengrust/__init__.pyi
cotengrust/cotengrust.cpython-39-aarch64-linux-gnu.so
cotengrust/py.typed
cotengrust-0.2.0.dist-info/RECORD
