Metadata-Version: 2.4
Name: cotengrust
Version: 0.2.0
Classifier: Programming Language :: Rust
Classifier: Programming Language :: Python :: Implementation :: CPython
Classifier: Programming Language :: Python :: Implementation :: PyPy
License-File: LICENSE
Summary: Fast contraction ordering primitives for tensor networks.
Author-email: Johnnie Gray <johnniemcgray@gmail.com>
Requires-Python: >=3.8
